Metadata-Version: 2.1
Name: spbstu-amml
Version: 1.2.2
Summary: modelhub
Home-page: 
Author: 
Requires-Python: >=3.8
License-File: LICENSE
